Metadata-Version: 1.1
Name: urlSigner
Version: 0.0.3
Summary: Library to sign a URL
Home-page: https://github.com/deanle17/fsecure-assignment
Author: deanle17
Author-email: lecungdinh@gmail.com
License: MIT
Download-URL: https://github.com/deanle17/urlSigner/archive/0.0.3.tar.gz
Keywords: url,signer
Platform: UNKNOWN
